beancount_n26/__init__.py
beancount_n26/utils/__init__.py
beancount_n26/utils/patterns_generation.py
beancount_n26-1.5.0.dist-info/LICENSE.txt
beancount_n26-1.5.0.dist-info/METADATA
beancount_n26-1.5.0.dist-info/WHEEL
beancount_n26-1.5.0.dist-info/RECORD
